kubekind/__init__.py
kubekind/__main__.py
kubekind/kind.py
kubekind/version.py
kubekind/resources/container.py
kubekind/resources/pod.py
tests/test_resources_context.py
tests/test_resources_def.py
tests/test_version.py
kubekind-0.0.1.dist-info/LICENSE
kubekind-0.0.1.dist-info/METADATA
kubekind-0.0.1.dist-info/WHEEL
kubekind-0.0.1.dist-info/entry_points.txt
kubekind-0.0.1.dist-info/top_level.txt
kubekind-0.0.1.dist-info/RECORD
