Metadata-Version: 2.1
Name: kubekind
Version: 0.0.1
Summary: Library to generate Kubernetes manifests using Python code
Home-page: https://github.com/joaompinto/kubekind
Author: João Pinto
Author-email: lamego.pinto@gmail.com
License: MIT
Requires-Python: >=3.9
License-File: LICENSE
Requires-Dist: rich
Requires-Dist: attrs
